{
  "version": "1.0.0",
  "rss": "<LINK TO RSS FEED>",
  "discord": {
    "clientId": "<FILL IN OR REMOVE DISCORD OBJECT>",
    "smallImageText": "<FILL IN OR REMOVE DISCORD OBJECT>",
    "smallImageKey": "<FILL IN OR REMOVE DISCORD OBJECT>"
  },
  "servers": [
    {
      "id": "Japsik-1.20.6",
      "name": "사부작",
      "description": "사부작",
      "icon": "https://static.japsik.xyz/assets/images/Japsik-Logo-jyukaaaaa.png",
      "version": "1.0.2",
      "address": "play.japsik.xyz:25565",
      "minecraftVersion": "1.20.6",
      "discord": {
        "shortId": "",
        "largeImageText": "",
        "largeImageKey": ""
      },
      "mainServer": true,
      "autoconnect": false,
      "modules": [
        {
          "id": "net.fabricmc:fabric-loader:0.15.11",
          "name": "Fabric (fabric-loader)",
          "type": "Fabric",
          "artifact": {
            "size": 1327691,
            "MD5": "b49fcf1bafc14bcda2472a0f060ebe41",
            "url": "https://raw.githubusercontent.com/Japsik-Server/JapsikServer-Static/main/assets/launcher/repo/lib/net/fabricmc/fabric-loader/0.15.11/fabric-loader-0.15.11.jar"
          },
          "subModules": [
            {
              "id": "1.20.6-fabric-0.15.11",
              "name": "Fabric (version.json)",
              "type": "VersionManifest",
              "artifact": {
                "size": 2849,
                "MD5": "73e17f027e21efbd15aef38fa507e432",
                "url": "https://raw.githubusercontent.com/Japsik-Server/JapsikServer-Static/main/assets/launcher/repo/versions/1.20.6-fabric-0.15.11/1.20.6-fabric-0.15.11.json"
              }
            },
            {
              "id": "org.ow2.asm:asm:9.6",
              "name": "Fabric (asm)",
              "type": "Library",
              "artifact": {
                "size": 123598,
                "MD5": "6f8bccf756f170d4185bb24c8c2d2020",
                "url": "https://raw.githubusercontent.com/Japsik-Server/JapsikServer-Static/main/assets/launcher/repo/lib/org/ow2/asm/asm/9.6/asm-9.6.jar"
              }
            },
            {
              "id": "org.ow2.asm:asm-analysis:9.6",
              "name": "Fabric (asm-analysis)",
              "type": "Library",
              "artifact": {
                "size": 34041,
                "MD5": "31c84ef7cc893fb278952ae2d6a2674f",
                "url": "https://raw.githubusercontent.com/Japsik-Server/JapsikServer-Static/main/assets/launcher/repo/lib/org/ow2/asm/asm-analysis/9.6/asm-analysis-9.6.jar"
              }
            },
            {
              "id": "org.ow2.asm:asm-commons:9.6",
              "name": "Fabric (asm-commons)",
              "type": "Library",
              "artifact": {
                "size": 72194,
                "MD5": "9e317c75534bd1da8c00a67c618ab288",
                "url": "https://raw.githubusercontent.com/Japsik-Server/JapsikServer-Static/main/assets/launcher/repo/lib/org/ow2/asm/asm-commons/9.6/asm-commons-9.6.jar"
              }
            },
            {
              "id": "org.ow2.asm:asm-tree:9.6",
              "name": "Fabric (asm-tree)",
              "type": "Library",
              "artifact": {
                "size": 51935,
                "MD5": "6062608f1a98afe1e853d01fa1221a9e",
                "url": "https://raw.githubusercontent.com/Japsik-Server/JapsikServer-Static/main/assets/launcher/repo/lib/org/ow2/asm/asm-tree/9.6/asm-tree-9.6.jar"
              }
            },
            {
              "id": "org.ow2.asm:asm-util:9.6",
              "name": "Fabric (asm-util)",
              "type": "Library",
              "artifact": {
                "size": 91131,
                "MD5": "bd3bc1c176a787373e9a031073c9574b",
                "url": "https://raw.githubusercontent.com/Japsik-Server/JapsikServer-Static/main/assets/launcher/repo/lib/org/ow2/asm/asm-util/9.6/asm-util-9.6.jar"
              }
            },
            {
              "id": "net.fabricmc:sponge-mixin:0.13.3+mixin.0.8.5",
              "name": "Fabric (sponge-mixin)",
              "type": "Library",
              "artifact": {
                "size": 1458875,
                "MD5": "9dcf01250f72212bf97f0fef55ba5acd",
                "url": "https://raw.githubusercontent.com/Japsik-Server/JapsikServer-Static/main/assets/launcher/repo/lib/net/fabricmc/sponge-mixin/0.13.3+mixin.0.8.5/sponge-mixin-0.13.3+mixin.0.8.5.jar"
              }
            },
            {
              "id": "net.fabricmc:intermediary:1.20.6",
              "name": "Fabric (intermediary)",
              "type": "Library",
              "artifact": {
                "size": 645866,
                "MD5": "f15d0e5260bfeccf2fdca0da114cac48",
                "url": "https://raw.githubusercontent.com/Japsik-Server/JapsikServer-Static/main/assets/launcher/repo/lib/net/fabricmc/intermediary/1.20.6/intermediary-1.20.6.jar"
              }
            }
          ]
        },
        {
          "id": "me.cominixo:betterf3:10.0.1@jar",
          "name": "BetterF3",
          "type": "FabricMod",
          "artifact": {
            "size": 1795643,
            "url": "https://raw.githubusercontent.com/Japsik-Server/JapsikServer-Static/main/assets/launcher/servers/Japsik-1.20.6/fabricmods/required/BetterF3-10.0.1-Fabric-1.20.6.jar",
            "MD5": "8e4930e4b11c615791728ac895389d60"
          }
        },
        {
          "id": "eu.midnightdust:blur:4.0.0@jar",
          "name": "Blur+ (Fabric)",
          "type": "FabricMod",
          "artifact": {
            "size": 76705,
            "url": "https://raw.githubusercontent.com/Japsik-Server/JapsikServer-Static/main/assets/launcher/servers/Japsik-1.20.6/fabricmods/optionalon/blur-4.0.0.jar",
            "MD5": "631d53d0a8eb86ed6e0d47e7d80498e2"
          },
          "required": {
            "value": false
          }
        },
        {
          "id": "nl.enjarai:cicada:0.7.2+1.20.5-and-above@jar",
          "name": "CICADA",
          "type": "FabricMod",
          "artifact": {
            "size": 84388,
            "url": "https://raw.githubusercontent.com/Japsik-Server/JapsikServer-Static/main/assets/launcher/servers/Japsik-1.20.6/fabricmods/optionalon/cicada-lib-0.7.2+1.20.5-and-above.jar",
            "MD5": "8c5343b1d4eadf737f2f561d148ccdd6"
          },
          "required": {
            "value": false
          }
        },
        {
          "id": "me.shedaniel.autoconfig.example:cloth-config:14.0.126@jar",
          "name": "Cloth Config v14",
          "type": "FabricMod",
          "artifact": {
            "size": 1144434,
            "url": "https://raw.githubusercontent.com/Japsik-Server/JapsikServer-Static/main/assets/launcher/servers/Japsik-1.20.6/fabricmods/required/cloth-config-14.0.126-fabric.jar",
            "MD5": "c7bec328b262e26e642dd0b2cd699050"
          }
        },
        {
          "id": "com.notryken:commandkeys:1.2.0@jar",
          "name": "CommandKeys",
          "type": "FabricMod",
          "artifact": {
            "size": 118889,
            "url": "https://raw.githubusercontent.com/Japsik-Server/JapsikServer-Static/main/assets/launcher/servers/Japsik-1.20.6/fabricmods/required/CommandKeys-Fabric-1.20.5-1.2.0.jar",
            "MD5": "0553f0ebe4d5ef29121eb2f91c209b3d"
          }
        },
        {
          "id": "me.pepperbell:continuity:3.0.0-beta.5+1.20.5@jar",
          "name": "Continuity",
          "type": "FabricMod",
          "artifact": {
            "size": 1009234,
            "url": "https://raw.githubusercontent.com/Japsik-Server/JapsikServer-Static/main/assets/launcher/servers/Japsik-1.20.6/fabricmods/optionalon/continuity-3.0.0-beta.5+1.20.5.jar",
            "MD5": "36ad54c49157899a0cbc1585f3657429"
          },
          "required": {
            "value": false
          }
        },
        {
          "id": "com.hypherionmc:craterlib:1.1.0@jar",
          "name": "CraterLib",
          "type": "FabricMod",
          "artifact": {
            "size": 1232562,
            "url": "https://raw.githubusercontent.com/Japsik-Server/JapsikServer-Static/main/assets/launcher/servers/Japsik-1.20.6/fabricmods/required/CraterLib-Fabric-1.20.4-1.1.0.jar",
            "MD5": "ca554377fd4d2f6823ba994e627544ae"
          }
        },
        {
          "id": "team.creative:creativecore:2.11.32@jar",
          "name": "CreativeCore",
          "type": "FabricMod",
          "artifact": {
            "size": 1143776,
            "url": "https://raw.githubusercontent.com/Japsik-Server/JapsikServer-Static/main/assets/launcher/servers/Japsik-1.20.6/fabricmods/required/CreativeCore_FABRIC_v2.11.32_mc1.20.6.jar",
            "MD5": "da312a2c0eefa38541d905f9e54e7011"
          }
        },
        {
          "id": "nl.enjarai.doabarrelroll:do_a_barrel_roll:3.6.0+1.20.6@jar",
          "name": "Do a Barrel Roll",
          "type": "FabricMod",
          "artifact": {
            "size": 507864,
            "url": "https://raw.githubusercontent.com/Japsik-Server/JapsikServer-Static/main/assets/launcher/servers/Japsik-1.20.6/fabricmods/optionalon/do_a_barrel_roll-fabric-3.6.0+1.20.6.jar",
            "MD5": "ade1c4a6feb690f2a7f83ff647c8c5a0"
          },
          "required": {
            "value": false
          }
        },
        {
          "id": "net.lostluma.dynamic_fps.impl.fabric.compat:dynamic_fps:3.4.3@jar",
          "name": "Dynamic FPS",
          "type": "FabricMod",
          "artifact": {
            "size": 94305,
            "url": "https://raw.githubusercontent.com/Japsik-Server/JapsikServer-Static/main/assets/launcher/servers/Japsik-1.20.6/fabricmods/required/dynamic-fps-3.4.3+minecraft-1.20.5-fabric.jar",
            "MD5": "45c4bb7b0db05d8261f968a980b419d0"
          }
        },
        {
          "id": "generated.fabricmod:fabric-api:0.99.4+1.20.6@jar",
          "name": "Fabric API",
          "type": "FabricMod",
          "artifact": {
            "size": 2230715,
            "url": "https://raw.githubusercontent.com/Japsik-Server/JapsikServer-Static/main/assets/launcher/servers/Japsik-1.20.6/fabricmods/required/fabric-api-0.99.4+1.20.6.jar",
            "MD5": "42478748f033622cf9afcae8e8228744"
          }
        },
        {
          "id": "generated.fabricmod:fabric-language-kotlin:1.11.0+kotlin.2.0.0@jar",
          "name": "Fabric Language Kotlin",
          "type": "FabricMod",
          "artifact": {
            "size": 7015315,
            "url": "https://raw.githubusercontent.com/Japsik-Server/JapsikServer-Static/main/assets/launcher/servers/Japsik-1.20.6/fabricmods/required/fabric-language-kotlin-1.11.0+kotlin.2.0.0.jar",
            "MD5": "ac91311ce91421ca52a96d2a4e4f078c"
          }
        },
        {
          "id": "randommcsomethin.fallingleaves:fallingleaves:1.15.8@jar",
          "name": "Falling Leaves",
          "type": "FabricMod",
          "artifact": {
            "size": 159666,
            "url": "https://raw.githubusercontent.com/Japsik-Server/JapsikServer-Static/main/assets/launcher/servers/Japsik-1.20.6/fabricmods/optionalon/fallingleaves-1.15.8+1.20.5.jar",
            "MD5": "18690b522329c3be97f4ea5b1e371300"
          },
          "required": {
            "value": false
          }
        },
        {
          "id": "de.keksuccino:fancymenu:3.2.3@jar",
          "name": "FancyMenu",
          "type": "FabricMod",
          "artifact": {
            "size": 2692710,
            "url": "https://raw.githubusercontent.com/Japsik-Server/JapsikServer-Static/main/assets/launcher/servers/Japsik-1.20.6/fabricmods/required/fancymenu_fabric_3.2.3_MC_1.20.6.jar",
            "MD5": "c7df95c10eb4b0b3ab0e1204b4541fe9"
          }
        },
        {
          "id": "com.wildfire.main:wildfire_gender:3.2.1+1.20.6@jar",
          "name": "Wildfire's Female Gender Mod",
          "type": "FabricMod",
          "artifact": {
            "size": 962271,
            "url": "https://raw.githubusercontent.com/Japsik-Server/JapsikServer-Static/main/assets/launcher/servers/Japsik-1.20.6/fabricmods/optionalon/Female-Gender-Mod-fabric-3.2.1+1.20.6.jar",
            "MD5": "65a2272b4091a1977b132db50f917960"
          },
          "required": {
            "value": false
          }
        },
        {
          "id": "generated.fabricmod:ferritecore:6.1.1@jar",
          "name": "FerriteCore",
          "type": "FabricMod",
          "artifact": {
            "size": 118182,
            "url": "https://raw.githubusercontent.com/Japsik-Server/JapsikServer-Static/main/assets/launcher/servers/Japsik-1.20.6/fabricmods/required/ferritecore-6.1.1-fabric.jar",
            "MD5": "89654e168d9f271b435f529f85976b1c"
          }
        },
        {
          "id": "dev.tr7zw:firstperson:2.4.1@jar",
          "name": "FirstPerson",
          "type": "FabricMod",
          "artifact": {
            "size": 114568,
            "url": "https://raw.githubusercontent.com/Japsik-Server/JapsikServer-Static/main/assets/launcher/servers/Japsik-1.20.6/fabricmods/optionaloff/firstperson-fabric-2.4.1-mc1.20.6.jar",
            "MD5": "0d6f1fd42b4d008802c9eed8048fe7bc"
          },
          "required": {
            "value": false,
            "def": false
          }
        },
        {
          "id": "link.infra:indium:1.0.30+mc1.20.4@jar",
          "name": "Indium",
          "type": "FabricMod",
          "artifact": {
            "size": 104805,
            "url": "https://raw.githubusercontent.com/Japsik-Server/JapsikServer-Static/main/assets/launcher/servers/Japsik-1.20.6/fabricmods/required/indium-1.0.30+mc1.20.4.jar",
            "MD5": "e0b3675f1e6e8f00da58d42ec1bd1be7"
          }
        },
        {
          "id": "me.pieking1215:invmove:0.8.6@jar",
          "name": "InvMove",
          "type": "FabricMod",
          "artifact": {
            "size": 127623,
            "url": "https://raw.githubusercontent.com/Japsik-Server/JapsikServer-Static/main/assets/launcher/servers/Japsik-1.20.6/fabricmods/optionalon/InvMove-1.20-0.8.6-Fabric.jar",
            "MD5": "3158af677982416dc21ba7aa04d611a3"
          },
          "required": {
            "value": false
          }
        },
        {
          "id": "generated.fabricmod:invmovecompats:0.3.2@jar",
          "name": "InvMoveCompats",
          "type": "FabricMod",
          "artifact": {
            "size": 102080,
            "url": "https://raw.githubusercontent.com/Japsik-Server/JapsikServer-Static/main/assets/launcher/servers/Japsik-1.20.6/fabricmods/optionalon/InvMoveCompats-1.20-0.3.2-Fabric.jar",
            "MD5": "2e4cb16cea2e2a765bd138cbb58ffaa0"
          },
          "required": {
            "value": false
          }
        },
        {
          "id": "generated.fabricmod:iris:1.7.0+mc1.20.6@jar",
          "name": "Iris",
          "type": "FabricMod",
          "artifact": {
            "size": 2698708,
            "url": "https://raw.githubusercontent.com/Japsik-Server/JapsikServer-Static/main/assets/launcher/servers/Japsik-1.20.6/fabricmods/required/iris-1.7.0+mc1.20.6.jar",
            "MD5": "3c550fff0aae1331134287230355a0dc"
          }
        },
        {
          "id": "de.keksuccino:konkrete:1.9.4@jar",
          "name": "Konkrete",
          "type": "FabricMod",
          "artifact": {
            "size": 785830,
            "url": "https://raw.githubusercontent.com/Japsik-Server/JapsikServer-Static/main/assets/launcher/servers/Japsik-1.20.6/fabricmods/required/konkrete_fabric_1.9.4_MC_1.20.5.jar",
            "MD5": "fc6c22dfe0f9d9c6c958672c73981574"
          }
        },
        {
          "id": "com.hyfata.najoan:koreanpatch:1.3.7-1.20.6@jar",
          "name": "Korean Patch",
          "type": "FabricMod",
          "artifact": {
            "size": 37284,
            "url": "https://raw.githubusercontent.com/Japsik-Server/JapsikServer-Static/main/assets/launcher/servers/Japsik-1.20.6/fabricmods/required/koreanpatch-1.3.7-1.20.6.jar",
            "MD5": "07b104b4515e87b8a09c3afdccf7d68f"
          }
        },
        {
          "id": "me.jellysquid.mods:lithium:0.12.3@jar",
          "name": "Lithium",
          "type": "FabricMod",
          "artifact": {
            "size": 684119,
            "url": "https://raw.githubusercontent.com/Japsik-Server/JapsikServer-Static/main/assets/launcher/servers/Japsik-1.20.6/fabricmods/required/lithium-fabric-mc1.20.6-0.12.3.jar",
            "MD5": "396668582f2219fa2f08419f5d4f1165"
          }
        },
        {
          "id": "de.keksuccino:melody:1.0.6@jar",
          "name": "Melody",
          "type": "FabricMod",
          "artifact": {
            "size": 188028,
            "url": "https://raw.githubusercontent.com/Japsik-Server/JapsikServer-Static/main/assets/launcher/servers/Japsik-1.20.6/fabricmods/required/melody_fabric_1.0.6_MC_1.20.5.jar",
            "MD5": "32f2cb851a1e682d1fdd5349791359a1"
          }
        },
        {
          "id": "com.terraformersmc:modmenu:10.0.0-beta.1@jar",
          "name": "Mod Menu",
          "type": "FabricMod",
          "artifact": {
            "size": 746627,
            "url": "https://raw.githubusercontent.com/Japsik-Server/JapsikServer-Static/main/assets/launcher/servers/Japsik-1.20.6/fabricmods/required/modmenu-10.0.0-beta.1.jar",
            "MD5": "db825ac6ef14a4d3e0237785fd73615f"
          }
        },
        {
          "id": "dev.tr7zw:notenoughanimations:1.7.3@jar",
          "name": "NotEnoughAnimations",
          "type": "FabricMod",
          "artifact": {
            "size": 418311,
            "url": "https://raw.githubusercontent.com/Japsik-Server/JapsikServer-Static/main/assets/launcher/servers/Japsik-1.20.6/fabricmods/optionalon/notenoughanimations-fabric-1.7.3-mc1.20.6.jar",
            "MD5": "65584f0aae0e84b9fd6bd1c2fa7939ff"
          },
          "required": {
            "value": false
          }
        },
        {
          "id": "su.plo.voice:plasmovoice:2.0.9@jar",
          "name": "Plasmo Voice",
          "type": "FabricMod",
          "artifact": {
            "size": 11685170,
            "url": "https://raw.githubusercontent.com/Japsik-Server/JapsikServer-Static/main/assets/launcher/servers/Japsik-1.20.6/fabricmods/required/plasmovoice-fabric-1.20.6-2.0.9.jar",
            "MD5": "c625e5a7d3205e26e3f93ba9c2fee483"
          }
        },
        {
          "id": "su.plo.voice.soundphysics:pv-addon-soundphysics:1.0.1@jar",
          "name": "Pv-addon-soundphysics",
          "type": "FabricMod",
          "artifact": {
            "size": 11185,
            "url": "https://raw.githubusercontent.com/Japsik-Server/JapsikServer-Static/main/assets/launcher/servers/Japsik-1.20.6/fabricmods/optionalon/pv-addon-soundphysics-1.0.1.jar",
            "MD5": "d4fe1b1f22e32efc59db8dd6fda990c6"
          },
          "required": {
            "value": false
          }
        },
        {
          "id": "me.flashyreese.mods.sodiumextra:sodium-extra:0.5.5+mc1.20.6-build.118@jar",
          "name": "Sodium Extra",
          "type": "FabricMod",
          "artifact": {
            "size": 374163,
            "url": "https://raw.githubusercontent.com/Japsik-Server/JapsikServer-Static/main/assets/launcher/servers/Japsik-1.20.6/fabricmods/required/sodium-extra-0.5.5+mc1.20.6-build.118.jar",
            "MD5": "1d0af7ea70c54e0dd4105045b86423ae"
          }
        },
        {
          "id": "me.jellysquid.mods:sodium:0.5.8+mc1.20.6@jar",
          "name": "Sodium",
          "type": "FabricMod",
          "artifact": {
            "size": 964688,
            "url": "https://raw.githubusercontent.com/Japsik-Server/JapsikServer-Static/main/assets/launcher/servers/Japsik-1.20.6/fabricmods/required/sodium-fabric-0.5.8+mc1.20.6.jar",
            "MD5": "71f1650662a552f4e26d2fa79408d6b1"
          }
        },
        {
          "id": "com.sonicether.soundphysics:sound_physics_remastered:1.20.6-1.4.2@jar",
          "name": "Sound Physics Remastered",
          "type": "FabricMod",
          "artifact": {
            "size": 195268,
            "url": "https://raw.githubusercontent.com/Japsik-Server/JapsikServer-Static/main/assets/launcher/servers/Japsik-1.20.6/fabricmods/optionalon/sound-physics-remastered-fabric-1.20.6-1.4.2.jar",
            "MD5": "4dd8c812279ff7aca365bb01bb6cf44a"
          },
          "required": {
            "value": false
          }
        },
        {
          "id": "net.wurstclient.zoom:wi_zoom:1.5-MC1.20.6@jar",
          "name": "WI Zoom",
          "type": "FabricMod",
          "artifact": {
            "size": 139407,
            "url": "https://raw.githubusercontent.com/Japsik-Server/JapsikServer-Static/main/assets/launcher/servers/Japsik-1.20.6/fabricmods/optionalon/WI-Zoom-1.5-MC1.20.6.jar",
            "MD5": "07a8025313ee3d32ab90c1133eed56ab"
          },
          "required": {
            "value": false
          }
        },
        {
          "id": "betterf3.json",
          "name": "betterf3.json",
          "type": "File",
          "artifact": {
            "size": 2492,
            "url": "https://raw.githubusercontent.com/Japsik-Server/JapsikServer-Static/main/assets/launcher/servers/Japsik-1.20.6/files/config/betterf3.json",
            "MD5": "d888e64e44a3ab79ec0750d56c011297",
            "path": "config/betterf3.json"
          }
        },
        {
          "id": "commandkeys.json",
          "name": "commandkeys.json",
          "type": "File",
          "artifact": {
            "size": 1478,
            "url": "https://raw.githubusercontent.com/Japsik-Server/JapsikServer-Static/main/assets/launcher/servers/Japsik-1.20.6/files/config/commandkeys.json",
            "MD5": "1a5c4cb0200c3dc686efe64268dac8e1",
            "path": "config/commandkeys.json"
          }
        },
        {
          "id": "japsik-logo-o-16.png",
          "name": "japsik-logo-o-16.png",
          "type": "File",
          "artifact": {
            "size": 695,
            "url": "https://raw.githubusercontent.com/Japsik-Server/JapsikServer-Static/main/assets/launcher/servers/Japsik-1.20.6/files/config/fancymenu/assets/japsik-logo-o-16.png",
            "MD5": "a0cb5e54c2f2c158093a067b6c6a97ad",
            "path": "config/fancymenu/assets/japsik-logo-o-16.png"
          }
        },
        {
          "id": "japsik-logo-o-32.icns",
          "name": "japsik-logo-o-32.icns",
          "type": "File",
          "artifact": {
            "size": 1820,
            "url": "https://raw.githubusercontent.com/Japsik-Server/JapsikServer-Static/main/assets/launcher/servers/Japsik-1.20.6/files/config/fancymenu/assets/japsik-logo-o-32.icns",
            "MD5": "4ece270de6786b677b217d86eb62f813",
            "path": "config/fancymenu/assets/japsik-logo-o-32.icns"
          }
        },
        {
          "id": "japsik-logo-o-32.png",
          "name": "japsik-logo-o-32.png",
          "type": "File",
          "artifact": {
            "size": 1135,
            "url": "https://raw.githubusercontent.com/Japsik-Server/JapsikServer-Static/main/assets/launcher/servers/Japsik-1.20.6/files/config/fancymenu/assets/japsik-logo-o-32.png",
            "MD5": "957a95c6623d6c5f065bf139b0d242b9",
            "path": "config/fancymenu/assets/japsik-logo-o-32.png"
          }
        },
        {
          "id": "japsik-logo-o.png",
          "name": "japsik-logo-o.png",
          "type": "File",
          "artifact": {
            "size": 17380,
            "url": "https://raw.githubusercontent.com/Japsik-Server/JapsikServer-Static/main/assets/launcher/servers/Japsik-1.20.6/files/config/fancymenu/assets/japsik-logo-o.png",
            "MD5": "a1ec0a4fe93d0616331321c672d8331f",
            "path": "config/fancymenu/assets/japsik-logo-o.png"
          }
        },
        {
          "id": "xmark.png",
          "name": "xmark.png",
          "type": "File",
          "artifact": {
            "size": 4736,
            "url": "https://raw.githubusercontent.com/Japsik-Server/JapsikServer-Static/main/assets/launcher/servers/Japsik-1.20.6/files/config/fancymenu/assets/xmark.png",
            "MD5": "74974c0f2bcf0d49e073de34a16c45e1",
            "path": "config/fancymenu/assets/xmark.png"
          }
        },
        {
          "id": "customizablemenus.txt",
          "name": "customizablemenus.txt",
          "type": "File",
          "artifact": {
            "size": 113,
            "url": "https://raw.githubusercontent.com/Japsik-Server/JapsikServer-Static/main/assets/launcher/servers/Japsik-1.20.6/files/config/fancymenu/customizablemenus.txt",
            "MD5": "be6af3e4d03f5b549353963c5d03962b",
            "path": "config/fancymenu/customizablemenus.txt"
          }
        },
        {
          "id": "join_multiplayer_screen_layout.txt",
          "name": "join_multiplayer_screen_layout.txt",
          "type": "File",
          "artifact": {
            "size": 8432,
            "url": "https://raw.githubusercontent.com/Japsik-Server/JapsikServer-Static/main/assets/launcher/servers/Japsik-1.20.6/files/config/fancymenu/customization/join_multiplayer_screen_layout.txt",
            "MD5": "8b25cea5e9f77968983f782394bdd9ec",
            "path": "config/fancymenu/customization/join_multiplayer_screen_layout.txt"
          }
        },
        {
          "id": "pause_screen_layout.txt",
          "name": "pause_screen_layout.txt",
          "type": "File",
          "artifact": {
            "size": 11522,
            "url": "https://raw.githubusercontent.com/Japsik-Server/JapsikServer-Static/main/assets/launcher/servers/Japsik-1.20.6/files/config/fancymenu/customization/pause_screen_layout.txt",
            "MD5": "21501078c89c8c41480408f7547db96d",
            "path": "config/fancymenu/customization/pause_screen_layout.txt"
          }
        },
        {
          "id": "title_screen_layout.txt",
          "name": "title_screen_layout.txt",
          "type": "File",
          "artifact": {
            "size": 16398,
            "url": "https://raw.githubusercontent.com/Japsik-Server/JapsikServer-Static/main/assets/launcher/servers/Japsik-1.20.6/files/config/fancymenu/customization/title_screen_layout.txt",
            "MD5": "9d043031d1397b70d029db5ca61c4857",
            "path": "config/fancymenu/customization/title_screen_layout.txt"
          }
        },
        {
          "id": "custom_gui_screens.txt",
          "name": "custom_gui_screens.txt",
          "type": "File",
          "artifact": {
            "size": 51,
            "url": "https://raw.githubusercontent.com/Japsik-Server/JapsikServer-Static/main/assets/launcher/servers/Japsik-1.20.6/files/config/fancymenu/custom_gui_screens.txt",
            "MD5": "106e52948415f0879c53304f50783b28",
            "path": "config/fancymenu/custom_gui_screens.txt"
          }
        },
        {
          "id": "element_layer_control.lewidget",
          "name": "element_layer_control.lewidget",
          "type": "File",
          "artifact": {
            "size": 197,
            "url": "https://raw.githubusercontent.com/Japsik-Server/JapsikServer-Static/main/assets/launcher/servers/Japsik-1.20.6/files/config/fancymenu/layout_editor/widgets/element_layer_control.lewidget",
            "MD5": "70546b71ee503f0bf790bfbd1a1b8c2d",
            "path": "config/fancymenu/layout_editor/widgets/element_layer_control.lewidget"
          }
        },
        {
          "id": "legacy_checklist.txt",
          "name": "legacy_checklist.txt",
          "type": "File",
          "artifact": {
            "size": 42,
            "url": "https://raw.githubusercontent.com/Japsik-Server/JapsikServer-Static/main/assets/launcher/servers/Japsik-1.20.6/files/config/fancymenu/legacy_checklist.txt",
            "MD5": "bc03e01c4f1bf1e24e9b86591baa512b",
            "path": "config/fancymenu/legacy_checklist.txt"
          }
        },
        {
          "id": "options.txt",
          "name": "options.txt",
          "type": "File",
          "artifact": {
            "size": 1873,
            "url": "https://raw.githubusercontent.com/Japsik-Server/JapsikServer-Static/main/assets/launcher/servers/Japsik-1.20.6/files/config/fancymenu/options.txt",
            "MD5": "47b8de7a682ed0938a51b8f3ea62f10e",
            "path": "config/fancymenu/options.txt"
          }
        },
        {
          "id": "dark.json",
          "name": "dark.json",
          "type": "File",
          "artifact": {
            "size": 4133,
            "url": "https://raw.githubusercontent.com/Japsik-Server/JapsikServer-Static/main/assets/launcher/servers/Japsik-1.20.6/files/config/fancymenu/ui_themes/dark.json",
            "MD5": "1fc916f1d20b24c5f0d2d138d19c49a4",
            "path": "config/fancymenu/ui_themes/dark.json"
          }
        },
        {
          "id": "light.json",
          "name": "light.json",
          "type": "File",
          "artifact": {
            "size": 4135,
            "url": "https://raw.githubusercontent.com/Japsik-Server/JapsikServer-Static/main/assets/launcher/servers/Japsik-1.20.6/files/config/fancymenu/ui_themes/light.json",
            "MD5": "adfba137b3d62c50a5186a4f6523a72a",
            "path": "config/fancymenu/ui_themes/light.json"
          }
        },
        {
          "id": "user_variables.db",
          "name": "user_variables.db",
          "type": "File",
          "artifact": {
            "size": 23,
            "url": "https://raw.githubusercontent.com/Japsik-Server/JapsikServer-Static/main/assets/launcher/servers/Japsik-1.20.6/files/config/fancymenu/user_variables.db",
            "MD5": "458e4f3f673e3fea22fb92bf76fcf912",
            "path": "config/fancymenu/user_variables.db"
          }
        },
        {
          "id": "server-entries.toml",
          "name": "server-entries.toml",
          "type": "File",
          "artifact": {
            "size": 150,
            "url": "https://raw.githubusercontent.com/Japsik-Server/JapsikServer-Static/main/assets/launcher/servers/Japsik-1.20.6/files/config/simple-rpc/server-entries.toml",
            "MD5": "2fca628745ebfdc5b64aa8101f507a36",
            "path": "config/simple-rpc/server-entries.toml"
          }
        },
        {
          "id": "simple-rpc.toml",
          "name": "simple-rpc.toml",
          "type": "File",
          "artifact": {
            "size": 8299,
            "url": "https://raw.githubusercontent.com/Japsik-Server/JapsikServer-Static/main/assets/launcher/servers/Japsik-1.20.6/files/config/simple-rpc/simple-rpc.toml",
            "MD5": "5024fc7e8d33a60bfe796404cf004fc0",
            "path": "config/simple-rpc/simple-rpc.toml"
          }
        },
        {
          "id": "BSL.zip",
          "name": "BSL.zip",
          "type": "File",
          "artifact": {
            "size": 940031,
            "url": "https://raw.githubusercontent.com/Japsik-Server/JapsikServer-Static/main/assets/launcher/servers/Japsik-1.20.6/files/shaderpacks/BSL.zip",
            "MD5": "13a81f3bfc3386c2dc154063bf52a385",
            "path": "shaderpacks/BSL.zip"
          }
        },
        {
          "id": "Chocapic13.zip",
          "name": "Chocapic13.zip",
          "type": "File",
          "artifact": {
            "size": 14149623,
            "url": "https://raw.githubusercontent.com/Japsik-Server/JapsikServer-Static/main/assets/launcher/servers/Japsik-1.20.6/files/shaderpacks/Chocapic13.zip",
            "MD5": "370978c21f154a0022c4d5b5703b790b",
            "path": "shaderpacks/Chocapic13.zip"
          }
        },
        {
          "id": "ComplementaryShaders.zip",
          "name": "ComplementaryShaders.zip",
          "type": "File",
          "artifact": {
            "size": 3454588,
            "url": "https://raw.githubusercontent.com/Japsik-Server/JapsikServer-Static/main/assets/launcher/servers/Japsik-1.20.6/files/shaderpacks/ComplementaryShaders.zip",
            "MD5": "7a48a5dd0f154855ed5a1f2def959ec3",
            "path": "shaderpacks/ComplementaryShaders.zip"
          }
        },
        {
          "id": "MakeUp-UltraFast.zip",
          "name": "MakeUp-UltraFast.zip",
          "type": "File",
          "artifact": {
            "size": 338348,
            "url": "https://raw.githubusercontent.com/Japsik-Server/JapsikServer-Static/main/assets/launcher/servers/Japsik-1.20.6/files/shaderpacks/MakeUp-UltraFast.zip",
            "MD5": "8809bc636dfde2d34219a37376513462",
            "path": "shaderpacks/MakeUp-UltraFast.zip"
          }
        },
        {
          "id": "SEUSPTGI.zip",
          "name": "SEUSPTGI.zip",
          "type": "File",
          "artifact": {
            "size": 4402258,
            "url": "https://raw.githubusercontent.com/Japsik-Server/JapsikServer-Static/main/assets/launcher/servers/Japsik-1.20.6/files/shaderpacks/SEUSPTGI.zip",
            "MD5": "a2f6feaf818e09dafd9a2afedcae5ba0",
            "path": "shaderpacks/SEUSPTGI.zip"
          }
        },
        {
          "id": "SildursVibrantShadersLite.zip",
          "name": "SildursVibrantShadersLite.zip",
          "type": "File",
          "artifact": {
            "size": 142247,
            "url": "https://raw.githubusercontent.com/Japsik-Server/JapsikServer-Static/main/assets/launcher/servers/Japsik-1.20.6/files/shaderpacks/SildursVibrantShadersLite.zip",
            "MD5": "e6294fc113d73c384a9e88e722d1b6da",
            "path": "shaderpacks/SildursVibrantShadersLite.zip"
          }
        },
        {
          "id": "xmark.png",
          "name": "xmark.png",
          "type": "File",
          "artifact": {
            "size": 4736,
            "url": "https://raw.githubusercontent.com/Japsik-Server/JapsikServer-Static/main/assets/launcher/servers/Japsik-1.20.6/files/xmark.png",
            "MD5": "74974c0f2bcf0d49e073de34a16c45e1",
            "path": "xmark.png"
          }
        }
      ]
    }
  ]
}